svd2json/__init__.py
svd2json/__version__.py
svd2json/py.typed
svd2json/svd2json.py
svd2json-0.1.6.dist-info/METADATA
svd2json-0.1.6.dist-info/WHEEL
svd2json-0.1.6.dist-info/entry_points.txt
svd2json-0.1.6.dist-info/top_level.txt
svd2json-0.1.6.dist-info/RECORD
