Metadata-Version: 2.1
Name: svd2json
Version: 0.1.6
Summary: Convert SVD file to json
Author-email: Ledger SAS <firmware@ledger.fr>
License: 
Classifier: Development Status :: 4 - Beta
Classifier: Intended Audience :: Developers
Classifier: Topic :: Software Development :: Build Tools
Classifier: License :: OSI Approved :: Apache Software License
Classifier: Programming Language :: Python :: 3
Classifier: Programming Language :: Python :: 3 :: Only
Classifier: Programming Language :: Python :: 3.10
Classifier: Programming Language :: Python :: 3.11
Classifier: Programming Language :: Python :: 3.12
Requires-Python: >=3.10
Provides-Extra: devel
Requires-Dist: coverage >=0.4 ; extra == 'devel'
Requires-Dist: pytest >=4.6 ; extra == 'devel'
Requires-Dist: cachetools >=5.3 ; extra == 'devel'
Provides-Extra: doc
Requires-Dist: Sphinx >=7.2.0 ; extra == 'doc'
Requires-Dist: sphinx-rtd-theme >=2.0.0 ; extra == 'doc'
Requires-Dist: sphinx-simplepdf >=1.6.0 ; extra == 'doc'
Provides-Extra: license
Requires-Dist: reuse >=3.0.0 ; extra == 'license'
Provides-Extra: lint
Requires-Dist: black <25.0,>=24.2 ; extra == 'lint'
Requires-Dist: flake8 <8.0,>=7.0 ; extra == 'lint'
Requires-Dist: flake8-html >=0.4.3 ; extra == 'lint'
Provides-Extra: type
Requires-Dist: mypy >=1.8.0 ; extra == 'type'
Requires-Dist: lxml >=4.8.0 ; extra == 'type'
